{
    "key": "group_581f69a3c46cf",
    "title": "Post",
    "fields": [
        {
            "key": "field_5a96e81a29e4d",
            "label": "General",
            "name": "",
            "type": "tab",
            "instructions": "",
            "required": 0,
            "conditional_logic": 0,
            "wrapper": {
                "width": "",
                "class": "",
                "id": ""
            },
            "placement": "top",
            "endpoint": 0
        },
        {
            "key": "field_581f69a781642",
            "label": "Introduction",
            "name": "introduction",
            "type": "textarea",
            "instructions": "",
            "required": 0,
            "conditional_logic": 0,
            "wrapper": {
                "width": "",
                "class": "",
                "id": ""
            },
            "default_value": "",
            "placeholder": "",
            "maxlength": "",
            "rows": 5,
            "new_lines": "wpautop",
            "readonly": 0,
            "disabled": 0
        },
        {
            "key": "field_59b58b3a8118c",
            "label": "Thumbnail",
            "name": "thumbnail",
            "type": "image",
            "instructions": "",
            "required": 0,
            "conditional_logic": 0,
            "wrapper": {
                "width": "",
                "class": "",
                "id": ""
            },
            "return_format": "array",
            "preview_size": "golden-small",
            "library": "all",
            "min_width": "",
            "min_height": "",
            "min_size": "",
            "max_width": "",
            "max_height": "",
            "max_size": "",
            "mime_types": ""
        },
        {
            "key": "field_5a96e82329e4e",
            "label": "SEO",
            "name": "",
            "type": "tab",
            "instructions": "",
            "required": 0,
            "conditional_logic": 0,
            "wrapper": {
                "width": "",
                "class": "",
                "id": ""
            },
            "placement": "top",
            "endpoint": 0
        },
        {
            "key": "field_5a96e82929e4f",
            "label": "Title",
            "name": "seo_title",
            "type": "text",
            "instructions": "",
            "required": 0,
            "conditional_logic": 0,
            "wrapper": {
                "width": "",
                "class": "",
                "id": ""
            },
            "default_value": "",
            "placeholder": "",
            "prepend": "",
            "append": "",
            "maxlength": "",
            "readonly": 0,
            "disabled": 0
        },
        {
            "key": "field_5a96e83129e50",
            "label": "Description",
            "name": "seo_description",
            "type": "textarea",
            "instructions": "",
            "required": 0,
            "conditional_logic": 0,
            "wrapper": {
                "width": "",
                "class": "",
                "id": ""
            },
            "default_value": "",
            "placeholder": "",
            "maxlength": "",
            "rows": 4,
            "new_lines": "",
            "readonly": 0,
            "disabled": 0
        }
    ],
    "location": [
        [
            {
                "param": "post_type",
                "operator": "==",
                "value": "post"
            }
        ],
        [
            {
                "param": "page_type",
                "operator": "==",
                "value": "front_page"
            }
        ]
    ],
    "menu_order": 0,
    "position": "acf_after_title",
    "style": "default",
    "label_placement": "left",
    "instruction_placement": "label",
    "hide_on_screen": [
        "the_content",
        "excerpt",
        "custom_fields",
        "discussion",
        "comments",
        "revisions",
        "slug",
        "author",
        "format",
        "page_attributes",
        "featured_image",
        "send-trackbacks"
    ],
    "active": 1,
    "description": "",
    "modified": 1519894206
}